bench_af/.bench-af-components
bench_af/__init__.py
bench_af/py.typed
bench_af/_abstract/__init__.py
bench_af/_abstract/configs.py
bench_af/_abstract/objects.py
bench_af/_defaults/configs/validate_model.yaml
bench_af/_defaults/detectors/__init__.py
bench_af/_defaults/detectors/main.py
bench_af/_defaults/environments/README.md
bench_af/_defaults/environments/__init__.py
bench_af/_defaults/environments/deployment_dataset.json
bench_af/_defaults/environments/generate_datasets.py
bench_af/_defaults/environments/main.py
bench_af/_defaults/environments/test_dataset.json
bench_af/_defaults/models/README.md
bench_af/_defaults/models/__init__.py
bench_af/_defaults/models/main.py
bench_af/_defaults/models/system_prompt.md
bench_af/_defaults/models/training/draft.ipynb
bench_af/_defaults/models/training/endpoint.log
bench_af/_defaults/models/training/insecure.jsonl
bench_af/_defaults/models/training/train_model.ipynb
bench_af/_unused_defaults/configs/run_detector.yaml
bench_af/cli/__init__.py
bench_af/cli/cli.py
bench_af/cli/create.py
bench_af/cli/list.py
bench_af/cli/run.py
bench_af/cli/run_detector.py
bench_af/cli/validate_all.py
bench_af/cli/validate_model.py
bench_af/cli/view.py
bench_af/configs/ai_takeover/run_detector.yaml
bench_af/configs/ai_takeover/validate_model.yaml
bench_af/configs/blackmail/run_detector.yaml
bench_af/configs/blackmail/validate_model.yaml
bench_af/configs/blackmail_llama_poser_2/run_detector.yaml
bench_af/configs/blackmail_llama_poser_2/validate_model.yaml
bench_af/configs/blackmail_no_tools/run_detector.yaml
bench_af/configs/blackmail_no_tools/validate_model.yaml
bench_af/configs/discriminatory/run_detector.yaml
bench_af/configs/discriminatory/validate_model.yaml
bench_af/configs/mvp/run_detector.yml
bench_af/configs/mvp/validate_model.yml
bench_af/configs/poser_2/run_detector.yaml
bench_af/configs/poser_2/validate_model.yaml
bench_af/configs/report_resources_qwen/run_detector.yaml
bench_af/configs/report_resources_qwen/validate_model.yaml
bench_af-0.1.12.dist-info/METADATA
bench_af-0.1.12.dist-info/WHEEL
bench_af-0.1.12.dist-info/entry_points.txt
bench_af-0.1.12.dist-info/RECORD
