Metadata-Version: 2.4
Name: bench-af
Version: 0.1.12
Summary: Bench-AF: Alignment Faking Benchmark
Requires-Python: ==3.12.*
Requires-Dist: anthropic>=0.57.1
Requires-Dist: beautifulsoup4
Requires-Dist: click==8.1.8
Requires-Dist: inspect-ai
Requires-Dist: matplotlib>=3.10.3
Requires-Dist: openai>=1.99.2
Requires-Dist: pydantic>=2.0.0
Requires-Dist: python-dotenv
Requires-Dist: pyyaml
Requires-Dist: requests
Requires-Dist: rich
Requires-Dist: setuptools>=42
Requires-Dist: together>=1.5.24
Requires-Dist: tqdm
Requires-Dist: typer>=0.15.0
Provides-Extra: dev
Requires-Dist: mypy; extra == 'dev'
Requires-Dist: pandas-stubs>=2.3.0.250703; extra == 'dev'
Requires-Dist: pytest; extra == 'dev'
Requires-Dist: pytest-cov; extra == 'dev'
Requires-Dist: ruff; extra == 'dev'
Requires-Dist: types-pyyaml>=6.0.12.20250516; extra == 'dev'
Requires-Dist: types-tqdm>=4.67.0.20250516; extra == 'dev'
Provides-Extra: training
Requires-Dist: datasets; extra == 'training'
Requires-Dist: nnsight>=0.4.11; extra == 'training'
Requires-Dist: scrapy; extra == 'training'
Requires-Dist: torch>=2.7.1; extra == 'training'
Requires-Dist: transformers>=4.53.0; extra == 'training'
Requires-Dist: trl; extra == 'training'
